pdfco/mcp/__init__.py
pdfco/mcp/models.py
pdfco/mcp/server.py
pdfco/mcp/services/__init__.py
pdfco/mcp/services/client.py
pdfco/mcp/services/pdf.py
pdfco/mcp/tools/__init__.py
pdfco/mcp/tools/apis/conversion.py
pdfco/mcp/tools/apis/document.py
pdfco/mcp/tools/apis/editing.py
pdfco/mcp/tools/apis/extraction.py
pdfco/mcp/tools/apis/file.py
pdfco/mcp/tools/apis/form.py
pdfco/mcp/tools/apis/job.py
pdfco/mcp/tools/apis/modification.py
pdfco/mcp/tools/apis/search.py
pdfco/mcp/tools/apis/searchable.py
pdfco/mcp/tools/apis/security.py
pdfco_mcp-0.0.7.dist-info/METADATA
pdfco_mcp-0.0.7.dist-info/WHEEL
pdfco_mcp-0.0.7.dist-info/entry_points.txt
pdfco_mcp-0.0.7.dist-info/licenses/LICENSE
pdfco_mcp-0.0.7.dist-info/RECORD
