Metadata-Version: 2.4
Name: pdfco-mcp
Version: 0.0.7
Summary: MCP server for PDF.Co
Project-URL: Homepage, https://pdf.co
Project-URL: Documentation, https://developer.pdf.co
Project-URL: Repository, https://github.com/pdfdotco/pdfco-mcp
Project-URL: Issues, https://github.com/pdfdotco/pdfco-mcp/issues
Author-email: "PDF.Co" <support@pdf.co>
License: MIT License
License-File: LICENSE
Keywords: mcp,pdf,pdf.co
Classifier: Intended Audience :: Developers
Classifier: Programming Language :: Python
Classifier: Programming Language :: Python :: 3
Classifier: Programming Language :: Python :: 3.10
Classifier: Programming Language :: Python :: 3.11
Classifier: Programming Language :: Python :: 3.12
Classifier: Programming Language :: Python :: 3.13
Requires-Python: >=3.10
Requires-Dist: fastmcp>=2.6.1
Requires-Dist: httpx>=0.28.1
Requires-Dist: mcp[cli]>=1.6.0
